toolkitr/__init__.py
toolkitr/_registry.py
toolkitr/_schema.py
toolkitr/_serializer.py
toolkitr-0.4.0.dist-info/METADATA
toolkitr-0.4.0.dist-info/WHEEL
toolkitr-0.4.0.dist-info/licenses/LICENSE
toolkitr-0.4.0.dist-info/RECORD
