Metadata-Version: 2.4
Name: toolkitr
Version: 0.4.0
Summary: Tool calling made easy
Project-URL: Homepage, https://github.com/undo76/toolkitr
Project-URL: Bug Tracker, https://github.com/undo76/toolkitr/issues
Project-URL: Documentation, https://github.com/undo76/toolkitr#readme
Author-email: Manolo Santos <manolo.santos@gmail.com>
License: MIT
License-File: LICENSE
Classifier: Development Status :: 4 - Beta
Classifier: Intended Audience :: Developers
Classifier: Programming Language :: Python :: 3
Classifier: Programming Language :: Python :: 3.11
Classifier: Topic :: Scientific/Engineering :: Artificial Intelligence
Classifier: Topic :: Software Development :: Libraries :: Python Modules
Requires-Python: ~=3.11
